CHANGES.txt
LICENSE.txt
MANIFEST.in
README.rst
setup.py
js/__init__.py
js.xeditable.egg-info/PKG-INFO
js.xeditable.egg-info/SOURCES.txt
js.xeditable.egg-info/dependency_links.txt
js.xeditable.egg-info/entry_points.txt
js.xeditable.egg-info/namespace_packages.txt
js.xeditable.egg-info/not-zip-safe
js.xeditable.egg-info/requires.txt
js.xeditable.egg-info/top_level.txt
js/xeditable/__init__.py
js/xeditable/test_xeditable.txt
js/xeditable/resources/bootstrap-editable/css/bootstrap-editable.css
js/xeditable/resources/bootstrap-editable/img/clear.png
js/xeditable/resources/bootstrap-editable/js/bootstrap-editable.js
js/xeditable/resources/bootstrap-editable/js/bootstrap-editable.min.js
js/xeditable/resources/jquery-editable/css/jquery-editable.css
js/xeditable/resources/jquery-editable/img/clear.png
js/xeditable/resources/jquery-editable/jquery-ui-datepicker/css/redmond/jquery-ui-1.10.2.custom.css
js/xeditable/resources/jquery-editable/jquery-ui-datepicker/css/redmond/jquery-ui-1.10.2.custom.min.css
js/xeditable/resources/jquery-editable/jquery-ui-datepicker/css/redmond/images/ui-bg_flat_0_aaaaaa_40x100.png
js/xeditable/resources/jquery-editable/jquery-ui-datepicker/css/redmond/images/ui-bg_flat_55_fbec88_40x100.png
js/xeditable/resources/jquery-editable/jquery-ui-datepicker/css/redmond/images/ui-bg_glass_75_d0e5f5_1x400.png
js/xeditable/resources/jquery-editable/jquery-ui-datepicker/css/redmond/images/ui-bg_glass_85_dfeffc_1x400.png
js/xeditable/resources/jquery-editable/jquery-ui-datepicker/css/redmond/images/ui-bg_glass_95_fef1ec_1x400.png
js/xeditable/resources/jquery-editable/jquery-ui-datepicker/css/redmond/images/ui-bg_gloss-wave_55_5c9ccc_500x100.png
js/xeditable/resources/jquery-editable/jquery-ui-datepicker/css/redmond/images/ui-bg_inset-hard_100_f5f8f9_1x100.png
js/xeditable/resources/jquery-editable/jquery-ui-datepicker/css/redmond/images/ui-bg_inset-hard_100_fcfdfd_1x100.png
js/xeditable/resources/jquery-editable/jquery-ui-datepicker/css/redmond/images/ui-icons_217bc0_256x240.png
js/xeditable/resources/jquery-editable/jquery-ui-datepicker/css/redmond/images/ui-icons_2e83ff_256x240.png
js/xeditable/resources/jquery-editable/jquery-ui-datepicker/css/redmond/images/ui-icons_469bdd_256x240.png
