Metadata-Version: 1.0
Name: js.xeditable
Version: 1.4.5
Summary: fanstatic xeditable.
Home-page: https://github.com/RedTurtle/js.xeditable
Author: RedTurtle Developers
Author-email: sviluppoplone@redturtle.it
License: BSD
Keywords: fanstatic xeditable redturtle
Platform: UNKNOWN
